[
  {
    "组合名称": "大智 (稳健智远)",
    "股票代码": 333,
    "股票名称": "美的集团",
    "配置比例 (%)": 9.71,
    "修改时间": 202509211549
  },
  {
    "组合名称": "大智 (稳健智远)",
    "股票代码": 518880,
    "股票名称": "黄金ETF",
    "配置比例 (%)": 2.06,
    "修改时间": 202509211549
  },
  {
    "组合名称": "大智 (稳健智远)",
    "股票代码": 510300,
    "股票名称": "沪深300ETF",
    "配置比例 (%)": 5.26,
    "修改时间": 202509211549
  },
  {
    "组合名称": "大智 (稳健智远)",
    "股票代码": 600085,
    "股票名称": "同仁堂",
    "配置比例 (%)": 1.92,
    "修改时间": 202509211549
  },
  {
    "组合名称": "大智 (稳健智远)",
    "股票代码": 601899,
    "股票名称": "紫金矿业",
    "配置比例 (%)": 0.98,
    "修改时间": 202509211549
  },
  {
    "组合名称": "大智 (稳健智远)",
    "股票代码": 513400,
    "股票名称": "道琼斯ETF",
    "配置比例 (%)": 5.11,
    "修改时间": 202509211549
  },
  {
    "组合名称": "大智 (稳健智远)",
    "股票代码": 831,
    "股票名称": "中国稀土",
    "配置比例 (%)": 9.21,
    "修改时间": 202509211549
  },
  {
    "组合名称": "大智 (稳健智远)",
    "股票代码": 89,
    "股票名称": "深圳机场",
    "配置比例 (%)": 5.03,
    "修改时间": 202509211549
  }
]