[
    {
        "代码": "000089",
        "名称": "深圳机场",
        "Price": 7.01,
        "Percent": 0.29,
        "Amount": 0.35,
        "PE_TTM": 23.02,
        "PB": 1.26,
        "update_time_bjt": "2025-10-14 10:34:56",
        "trade_date": "2025-10-14"
    },
    {
        "代码": "000333",
        "名称": "美的集团",
        "Price": 72.35,
        "Percent": 0.75,
        "Amount": 12.58,
        "PE_TTM": 10.68,
        "PB": 2.57,
        "update_time_bjt": "2025-10-14 10:34:56",
        "trade_date": "2025-10-14"
    },
    {
        "代码": "000831",
        "名称": "中国稀土",
        "Price": 61.62,
        "Percent": 2.46,
        "Amount": 53.17,
        "PE_TTM": 202.19,
        "PB": 13.62,
        "update_time_bjt": "2025-10-14 10:34:56",
        "trade_date": "2025-10-14"
    },
    {
        "代码": "600085",
        "名称": "同仁堂",
        "Price": 34.32,
        "Percent": 0.59,
        "Amount": 1.24,
        "PE_TTM": 24.89,
        "PB": 3.5,
        "update_time_bjt": "2025-10-14 10:34:56",
        "trade_date": "2025-10-14"
    },
    {
        "代码": "601899",
        "名称": "紫金矿业",
        "Price": 30.67,
        "Percent": -2.01,
        "Amount": 73.02,
        "PE_TTM": 17.5,
        "PB": 5.8,
        "update_time_bjt": "2025-10-14 10:34:56",
        "trade_date": "2025-10-14"
    },
    {
        "代码": "000725",
        "名称": "京东方Ａ",
        "Price": 4.12,
        "Percent": 0.24,
        "Amount": 12.58,
        "PE_TTM": 23.74,
        "PB": 1.16,
        "update_time_bjt": "2025-10-14 10:34:56",
        "trade_date": "2025-10-14"
    },
    {
        "代码": "001380",
        "名称": "华纬科技",
        "Price": 26.98,
        "Percent": -0.44,
        "Amount": 0.32,
        "PE_TTM": 28.78,
        "PB": 4.12,
        "update_time_bjt": "2025-10-14 10:34:56",
        "trade_date": "2025-10-14"
    },
    {
        "代码": "002074",
        "名称": "国轩高科",
        "Price": 42.94,
        "Percent": 0.09,
        "Amount": 16.06,
        "PE_TTM": 106.21,
        "PB": 2.96,
        "update_time_bjt": "2025-10-14 10:34:56",
        "trade_date": "2025-10-14"
    },
    {
        "代码": "601878",
        "名称": "浙商证券",
        "Price": 11.63,
        "Percent": 0.78,
        "Amount": 2.34,
        "PE_TTM": 23.15,
        "PB": 1.48,
        "update_time_bjt": "2025-10-14 10:34:56",
        "trade_date": "2025-10-14"
    },
    {
        "代码": "603119",
        "名称": "浙江荣泰",
        "Price": 92.92,
        "Percent": -4.45,
        "Amount": 8.99,
        "PE_TTM": 136.94,
        "PB": 17.96,
        "update_time_bjt": "2025-10-14 10:34:56",
        "trade_date": "2025-10-14"
    },
    {
        "代码": "600531",
        "名称": "豫光金铅",
        "Price": 15.04,
        "Percent": 3.16,
        "Amount": 12.17,
        "PE_TTM": 16.92,
        "PB": 2.87,
        "update_time_bjt": "2025-10-14 10:34:56",
        "trade_date": "2025-10-14"
    },
    {
        "代码": "301291",
        "名称": "明阳电气",
        "Price": 48.12,
        "Percent": -1.31,
        "Amount": 2.69,
        "PE_TTM": 24.52,
        "PB": 3.15,
        "update_time_bjt": "2025-10-14 10:34:56",
        "trade_date": "2025-10-14"
    },
    {
        "代码": "603301",
        "名称": "振德医疗",
        "Price": 65.3,
        "Percent": 8.04,
        "Amount": 4.9,
        "PE_TTM": 68.09,
        "PB": 3.09,
        "update_time_bjt": "2025-10-14 10:34:56",
        "trade_date": "2025-10-14"
    },
    {
        "代码": "603878",
        "名称": "武进不锈",
        "Price": 12.1,
        "Percent": 5.58,
        "Amount": 4.28,
        "PE_TTM": 44.96,
        "PB": 2.61,
        "update_time_bjt": "2025-10-14 10:34:56",
        "trade_date": "2025-10-14"
    },
    {
        "代码": "001326",
        "名称": "联域股份",
        "Price": 51.25,
        "Percent": 2.73,
        "Amount": 0.48,
        "PE_TTM": 116.13,
        "PB": 3.08,
        "update_time_bjt": "2025-10-14 10:34:56",
        "trade_date": "2025-10-14"
    },
    {
        "代码": "688103",
        "名称": "国力电子",
        "Price": 74.98,
        "Percent": -2.84,
        "Amount": 0.92,
        "PE_TTM": 100.0,
        "PB": 6.38,
        "update_time_bjt": "2025-10-14 10:34:56",
        "trade_date": "2025-10-14"
    },
    {
        "代码": "000603",
        "名称": "盛达资源",
        "Price": 28.65,
        "Percent": 0.1,
        "Amount": 6.8,
        "PE_TTM": 141.0,
        "PB": 6.52,
        "update_time_bjt": "2025-10-14 10:34:56",
        "trade_date": "2025-10-14"
    },
    {
        "代码": "300842",
        "名称": "帝科股份",
        "Price": 69.22,
        "Percent": -3.46,
        "Amount": 3.77,
        "PE_TTM": 70.28,
        "PB": 5.42,
        "update_time_bjt": "2025-10-14 10:34:56",
        "trade_date": "2025-10-14"
    },
    {
        "代码": "601126",
        "名称": "四方股份",
        "Price": 23.59,
        "Percent": 1.07,
        "Amount": 10.29,
        "PE_TTM": 20.64,
        "PB": 4.38,
        "update_time_bjt": "2025-10-14 10:34:56",
        "trade_date": "2025-10-14"
    },
    {
        "代码": "000021",
        "名称": "深科技",
        "Price": 31.06,
        "Percent": -1.05,
        "Amount": 42.76,
        "PE_TTM": 53.87,
        "PB": 3.95,
        "update_time_bjt": "2025-10-14 10:34:56",
        "trade_date": "2025-10-14"
    },
    {
        "代码": "605056",
        "名称": "咸亨国际",
        "Price": 16.97,
        "Percent": -0.93,
        "Amount": 0.49,
        "PE_TTM": 56.47,
        "PB": 4.3,
        "update_time_bjt": "2025-10-14 10:34:56",
        "trade_date": "2025-10-14"
    },
    {
        "代码": "000006",
        "名称": "深振业Ａ",
        "Price": 13.84,
        "Percent": 5.41,
        "Amount": 16.74,
        "PE_TTM": -131.62,
        "PB": 3.5,
        "update_time_bjt": "2025-10-14 10:34:56",
        "trade_date": "2025-10-14"
    },
    {
        "代码": "000685",
        "名称": "中山公用",
        "Price": 13.82,
        "Percent": -4.16,
        "Amount": 6.17,
        "PE_TTM": 14.17,
        "PB": 1.16,
        "update_time_bjt": "2025-10-14 10:34:56",
        "trade_date": "2025-10-14"
    },
    {
        "代码": "002487",
        "名称": "大金重工",
        "Price": 52.89,
        "Percent": 1.71,
        "Amount": 10.76,
        "PE_TTM": 30.86,
        "PB": 4.34,
        "update_time_bjt": "2025-10-14 10:34:56",
        "trade_date": "2025-10-14"
    },
    {
        "代码": "600105",
        "名称": "XD永鼎股",
        "Price": 15.52,
        "Percent": -4.55,
        "Amount": 32.45,
        "PE_TTM": 35.62,
        "PB": 6.9,
        "update_time_bjt": "2025-10-14 10:34:56",
        "trade_date": "2025-10-14"
    },
    {
        "代码": "600489",
        "名称": "中金黄金",
        "Price": 25.86,
        "Percent": 1.41,
        "Amount": 21.6,
        "PE_TTM": 23.26,
        "PB": 4.43,
        "update_time_bjt": "2025-10-14 10:34:56",
        "trade_date": "2025-10-14"
    },
    {
        "代码": "600641",
        "名称": "万业企业",
        "Price": 23.0,
        "Percent": -1.08,
        "Amount": 7.85,
        "PE_TTM": 262.27,
        "PB": 2.62,
        "update_time_bjt": "2025-10-14 10:34:56",
        "trade_date": "2025-10-14"
    },
    {
        "代码": "603799",
        "名称": "华友钴业",
        "Price": 67.85,
        "Percent": -3.73,
        "Amount": 58.54,
        "PE_TTM": 23.77,
        "PB": 2.85,
        "update_time_bjt": "2025-10-14 10:34:56",
        "trade_date": "2025-10-14"
    },
    {
        "代码": "688409",
        "名称": "富创精密",
        "Price": 86.3,
        "Percent": -4.71,
        "Amount": 5.82,
        "PE_TTM": 1076.29,
        "PB": 5.79,
        "update_time_bjt": "2025-10-14 10:34:56",
        "trade_date": "2025-10-14"
    },
    {
        "代码": "688596",
        "名称": "正帆科技",
        "Price": 46.3,
        "Percent": -5.01,
        "Amount": 7.55,
        "PE_TTM": 71.96,
        "PB": 3.78,
        "update_time_bjt": "2025-10-14 10:34:56",
        "trade_date": "2025-10-14"
    },
    {
        "代码": "688691",
        "名称": "灿芯股份",
        "Price": 156.43,
        "Percent": 8.63,
        "Amount": 16.45,
        "PE_TTM": -154.16,
        "PB": 14.57,
        "update_time_bjt": "2025-10-14 10:34:56",
        "trade_date": "2025-10-14"
    },
    {
        "代码": "HK01810",
        "名称": "小米集团-W",
        "Price": 49.14,
        "Percent": 0.12,
        "Amount": 27.25,
        "update_time_bjt": "2025-10-14 10:34:56",
        "trade_date": "2025-10-14"
    },
    {
        "代码": "510300",
        "名称": "沪深300ETF",
        "Price": 4.703,
        "Percent": 0.23,
        "Amount": 20.21,
        "update_time_bjt": "2025-10-14 10:34:56",
        "trade_date": "2025-10-14"
    },
    {
        "代码": "513400",
        "名称": "道琼斯ETF",
        "Price": 1.19,
        "Percent": 0.68,
        "Amount": 0.45,
        "update_time_bjt": "2025-10-14 10:34:56",
        "trade_date": "2025-10-14"
    },
    {
        "代码": "518880",
        "名称": "黄金ETF",
        "Price": 9.07,
        "Percent": 2.38,
        "Amount": 29.04,
        "update_time_bjt": "2025-10-14 10:34:56",
        "trade_date": "2025-10-14"
    },
    {
        "代码": "159781",
        "名称": "科创创业ETF",
        "Price": 0.869,
        "Percent": -1.7,
        "Amount": 1.61,
        "update_time_bjt": "2025-10-14 10:34:56",
        "trade_date": "2025-10-14"
    },
    {
        "代码": "513100",
        "名称": "纳指ETF",
        "Price": 1.85,
        "Percent": 1.15,
        "Amount": 3.62,
        "update_time_bjt": "2025-10-14 10:34:56",
        "trade_date": "2025-10-14"
    },
    {
        "代码": "513290",
        "名称": "纳指生物科技ETF",
        "Price": 1.324,
        "Percent": -0.45,
        "Amount": 0.24,
        "update_time_bjt": "2025-10-14 10:34:56",
        "trade_date": "2025-10-14"
    },
    {
        "代码": "510050",
        "名称": "上证50ETF",
        "Price": 3.116,
        "Percent": 0.48,
        "Amount": 8.49,
        "update_time_bjt": "2025-10-14 10:34:56",
        "trade_date": "2025-10-14"
    }
]